CHANGES.rst
LICENSE
LICENSE.txt
MANIFEST.in
README.rst
setup.py
vulcan/__init__.py
vulcan/meta_aws.py
vulcan/aws/__init__.py
vulcan/aws/_common.py
vulcan/aws/shared.py
vulcan/aws/services/__init__.py
vulcan/aws/services/_acm.py
vulcan/aws/services/_cloudformation.py
vulcan/aws/services/_cloudfront.py
vulcan/aws/services/_ec2.py
vulcan/aws/services/_iam.py
vulcan/aws/services/_lambda.py
vulcan/aws/services/_logs.py
vulcan/aws/services/_s3.py
vulcan/aws/services/_session.py
vulcan_aws.egg-info/PKG-INFO
vulcan_aws.egg-info/SOURCES.txt
vulcan_aws.egg-info/dependency_links.txt
vulcan_aws.egg-info/requires.txt
vulcan_aws.egg-info/top_level.txt