Metadata-Version: 2.1
Name: vulcan-aws
Version: 0.2.43
Summary: Amazon AWS boto3 helper libs.
Home-page: https://code.exrny.com/opensource/vulcan-aws/
Author: Peter Salnikov
Author-email: opensource@exrny.com
License: MIT License
Keywords: framework
Classifier: Development Status :: 4 - Beta
Classifier: Environment :: Console
Classifier: Intended Audience :: System Administrators
Classifier: Intended Audience :: Developers
Classifier: License :: OSI Approved :: MIT License
Classifier: Programming Language :: Python :: 2
Classifier: Programming Language :: Python :: 3
License-File: LICENSE
License-File: LICENSE.txt
